{"Vanilla E Reward":{"name":"Vanilla E Reward","url":"http://www.vanillaereward.com","time_taken":4929},"Vanilla Prepaid":{"name":"Vanilla Prepaid","url":"http://www.vanillaprepaid.com","time_taken":5346},"Alabama GiftCard":{"name":"Alabama GiftCard","url":"http://www.alabamagiftcard.com","time_taken":5565},"RiteAid Promo":{"name":"RiteAid Promo","url":"http://www.riteaidpromocode.com","time_taken":393},"WalmartAcademy":{"name":"WalmartAcademy","url":"http://www.walmartacademycard.com","time_taken":7491},"My Vanila Canada":{"name":"My Vanila Canada","url":"http://www.myvanillacard.com","time_taken":3890},"One Vanilla":{"name":"One Vanilla","url":"https://onevanilla.com","time_taken":5677},"MyVanilla Balance":{"name":"MyVanilla Balance","url":"http://www.myvanillabalance.com","time_taken":6671},"Vanilla MasterCard":{"name":"Vanilla MasterCard","url":"http://www.vanillamastercard.com","time_taken":11247},"Vanilla Reward":{"name":"Vanilla Reward","url":"http://www.vanillareward.com","time_taken":4565},"MyVanilla US":{"name":"MyVanilla US","url":"http://www.myvanilladebitcard.com","time_taken":2999},"MyIncentives":{"name":"MyIncentives","url":"http://www.myincentivescard.com","time_taken":5810},"Stripes":{"name":"Stripes","url":"http://www.stripesgiftcard.com","time_taken":10209},"Vanilla Reload":{"name":"Vanilla Reload","url":"http://www.vanillareload.com","time_taken":1392},"NextCala":{"name":"NextCala","url":"https://www.nextcala.com","time_taken":1485},"ReloadandSave":{"name":"ReloadandSave","url":"http://www.reloadandsave.com","time_taken":8566},"MyBalance Now":{"name":"MyBalance Now","url":"http://www.mybalancenow.com","time_taken":1798},"Vanilla Visa":{"name":"Vanilla Visa","url":"http://www.vanillavisa.com","time_taken":16917},"Vanilla BillPay":{"name":"Vanilla BillPay","url":"http://www.vanillabillpay.com","time_taken":17049},"Wellness":{"name":"Wellness","url":"http://wellnesshealthvisacard.com","time_taken":1985},"JHPreferred":{"name":"JHPreferred","url":"http://www.jhpreferred.com","time_taken":2275},"VanillaRewardCard":{"name":"VanillaRewardCard","url":"http://www.vanillarewardcard.com","time_taken":3665},"Vanilla Direct":{"name":"Vanilla Direct","url":"https://www.vanilladirect.com","time_taken":5167},"Rite aid reward":{"name":"Rite aid reward","url":"http://www.riteaidrewardcode.com","time_taken":5552},"UFan GiftCard":{"name":"UFan GiftCard","url":"http://www.ufangiftcards.com","time_taken":6032},"AmidaCare":{"name":"AmidaCare","url":"http://www.amidacarecard.com","time_taken":6307},"PALottery GiftCard":{"name":"PALottery GiftCard","url":"http://www.palotterygiftcard.com","time_taken":7616},"Ohana":{"name":"Ohana","url":"http://www.cfnarewardcard.com","time_taken":7777},"RiteAid Olympics":{"name":"RiteAid Olympics","url":"http://www.collect4rewardcards.com","time_taken":7997},"Kodak":{"name":"Kodak","url":"http://www.nrpcard.com","time_taken":8160},"Essilor Rebate":{"name":"Essilor Rebate","url":"http://www.essilorrebatecard.com","time_taken":8837},"RiteAid Reward":{"name":"RiteAid Reward","url":"http://www.riteaidrewardcard.com","time_taken":9376},"DFC Momentum":{"name":"DFC Momentum","url":"http://www.momentumcardbalance.com","time_taken":9631},"Vanilla Gift":{"name":"Vanilla Gift","url":"http://www.vanillagift.com","time_taken":20479}}